nbweb/__init__.py
nbweb/app.py
nbweb/cli.py
nbweb/data.json
nbweb/page.py
nbweb/parser.py
nbweb-0.0.7.dist-info/LICENSE
nbweb-0.0.7.dist-info/METADATA
nbweb-0.0.7.dist-info/WHEEL
nbweb-0.0.7.dist-info/entry_points.txt
nbweb-0.0.7.dist-info/top_level.txt
nbweb-0.0.7.dist-info/RECORD
