Metadata-Version: 2.1
Name: nbweb
Version: 0.0.7
Summary: an application to simplify web data
Author-email: Subrat Lima <subrat.k.lima@protonmail.com>
Project-URL: Homepage, https://github.com/subrat-lima/nbweb
Project-URL: Issues, https://github.com/subrat-lima/nbweb/issues
Classifier: Programming Language :: Python :: 3
Classifier: License :: OSI Approved :: MIT License
Requires-Python: >=3.11
License-File: LICENSE
Requires-Dist: httpx
Requires-Dist: parsel
Requires-Dist: fake-useragent
Provides-Extra: dev
Requires-Dist: nbweb[formatter,test] ; extra == 'dev'
Provides-Extra: formatter
Requires-Dist: black ; extra == 'formatter'
Provides-Extra: test
Requires-Dist: pytest ; extra == 'test'
